{
  "group": "ambyss",
  "type": "minecraft:crafting_shaped",
  "pattern": [
    "012",
    "345",
    "6 8"
  ],
  "key": {
    "0": {
      "item": "ambyss:cryoite"
    },
    "1": {
      "item": "ambyss:cryoite"
    },
    "2": {
      "item": "ambyss:cryoite"
    },
    "3": {
      "item": "ambyss:cryoite"
    },
    "4": {
      "item": "ambyss:topaz_armor_leggings"
    },
    "5": {
      "item": "ambyss:cryoite"
    },
    "6": {
      "item": "ambyss:cryoite"
    },
    "8": {
      "item": "ambyss:cryoite"
    }
  },
  "result": {
    "item": "ambyss:cryoite_armor_leggings",
    "count": 1
  }
}